setup.py
timestreamCLI/resizeTimestream.py
timestreamCLI.egg-info/PKG-INFO
timestreamCLI.egg-info/SOURCES.txt
timestreamCLI.egg-info/dependency_links.txt
timestreamCLI.egg-info/requires.txt
timestreamCLI.egg-info/top_level.txt