Metadata-Version: 1.1
Name: timestreamCLI
Version: 0.0a1
Summary: 
